{
  "articles": [
    {
      "id": 1,
      "title": "Understanding JSON",
      "content": "JSON stands for JavaScript Object Notation and is a lightweight data interchange format."
    },
    {
      "id": 2,
      "title": "Getting Started with JavaScript",
      "content": "JavaScript is a versatile programming language primarily used for web development."
    },
    {
      "id": 3,
      "title": "Exploring Node.js",
      "content": "Node.js is a runtime environment that allows you to run JavaScript on the server side."
    }
  ]
}
